Workbook

Sheet Sheet1
B1: Buying Split | C1: Occasion | D1: Description
B2: Essential Quality | C2: Playwear, Lounging | D2: Reliable, well-made basics for daily use, without the brand markup. | G2: Add 5 Light Essentials (Ships Free)
B3: Premium Standard | C3: Outings, Daycare/School, Socializing | D3: Popular brands and stylish designs offering trusted quality. | G3: Include up to 5 small items (socks, innerwear, light towels, or accessories) at no extra shipping cost.
B4: High-End Exclusive | C4: Special Occasion, Gifts, Investment pieces, Event wear | D4: Luxury designer labels and exclusive items with elite brand status.
A7: Who do you regularly shop for? (Select all that apply)" | J7: Standard Retail & Sales | O7: Avg. Weight(Kg)
B8: Category | C8: Typical Buying Cycle | D8: Clothing Requirement | E8: Buying Split | F8: Buying % | G8: Occasion | H8: Brands in Canada | I8: Wardrobe Qty (Replenishment) | J8: Canada Avg Price per item | K8: Canada Price | L8: India Avg RS price | M8: India Avg Price | N8: Buying via India | O8: Summer | P8: Winter | Q8: Mix | R8: Shipping Price (Cad) | S8: Total | T8: Difference
B9: Babies & Toddlers (Ages 0-4) | C9: Every 3 to 6 months | D9: 24 Items: 14 Tops, 10 Bottoms | E9: Essential Quality | F9: 0.6 | G9: Playwear, Lounging | H9: Walmart, Old Navy, Carter's basics | I9: 14 | J9: 8 | K9: =J9*I9 -> 112 | L9: =M9*67 -> 201 | M9: 3 | N9: 42
B10: micro-text: Frequent size changes | E10: Premium Standard | F10: 0.35 | G10: Daycare, Outings | H10: Zara, H&M, Gap Kids | I10: 8 | J10: 18 | K10: =J10*I10 -> 144 | L10: =M10*67 -> 536 | M10: 8 | N10: 64
E11: High-End Exclusive | F11: 0.05 | G11: Special Occasions | H11: Boutiques, Ralph Lauren Baby | I11: 2 | J11: 45 | K11: =J11*I11 -> 90 | L11: =M11*67 -> 1005 | M11: 15 | N11: 30
B12: Total | I12: =SUM(I9:I11) -> 24 | K12: =SUM(K9:K11) -> 346 | N12: =SUM(N9:N11) -> 136 | O12: 2.5 | P12: ='Shipping Rate'!H2 -> 4.5 | Q12: ='Shipping Rate'!I2 -> 3.5 | R12: 94 | S12: =R12+N12 -> 230 | T12: =K12-S12 -> 116
B13: Growing Kids (Ages 5-10) | C13: Every 12 months (Annual) | D13: 20 Items: 12 Tops, 8 Bottoms | E13: Essential Quality | F13: 0.5 | G13: Play clothes, Lounging | H13: Walmart, Old Navy, Joe Fresh | I13: 10 | J13: 10 | K13: =J13*I13 -> 100 | L13: =M13*67 -> 335 | M13: 5 | N13: =M13*I13 -> 50
B14: micro-text: Steady, annual size updates | E14: Premium Standard | F14: 0.4 | G14: School, Outings | H14: Zara, H&M, Gap Kids | I14: 8 | J14: 22 | K14: =J14*I14 -> 176 | L14: =M14*67 -> 670 | M14: 10 | N14: =M14*I14 -> 80
E15: High-End Exclusive | F15: 0.1 | G15: Special Occasions, Gifts | H15: Boutiques, Ralph Lauren Kids, Roots | I15: 2 | J15: 55 | K15: =J15*I15 -> 110 | L15: =M15*67 -> 1206 | M15: 18 | N15: =M15*I15 -> 36
B16: Total | I16: =SUM(I13:I15) -> 20 | K16: =SUM(K13:K15) -> 386 | N16: =SUM(N13:N15) -> 166 | O16: 3 | P16: 6 | Q16: 4.5 | R16: 110 | S16: =R16+N16 -> 276 | T16: =K16-S16 -> 110
B17: Teens (Ages 11-17) | C17: Every 6 to 12 months (Variable) | D17: 17 Items: 10 Tops, 7 Bottoms | E17: Essential Quality | F17: 0.3 | G17: Lounging, Undershirts | H17: Walmart, Old Navy basics, Amazon Essentials | I17: 5 | J17: 15 | K17: =J17*I17 -> 75 | L17: =M17*67 -> 402 | M17: 6 | N17: =M17*I17 -> 30
B18: micro-text: Unpredictable growth spurts | E18: Premium Standard | F18: 0.6 | G18: School, Socializing | H18: American Eagle, Zara, Nike, Hollister | I18: 10 | J18: 35 | K18: =J18*I18 -> 350 | L18: =M18*67 -> 1005 | M18: 15 | N18: =M18*I18 -> 150
E19: High-End Exclusive | F19: 0.1 | G19: Special Occasions, Gifts | H19: Lululemon, Aritzia, Boutique Streetwear | I19: 2 | J19: 80 | K19: =J19*I19 -> 160 | L19: =M19*67 -> 1675 | M19: 25 | N19: =M19*I19 -> 50
B20: Total | I20: =SUM(I17:I19) -> 17 | K20: =SUM(K17:K19) -> 585 | N20: =SUM(N17:N19) -> 230 | O20: ='Shipping Rate'!G4 -> 4 | P20: 7.5 | Q20: 5.5 | R20: 126 | S20: =R20+N20 -> 356 | T20: =K20-S20 -> 229
B21: Adults (Ages 18+) | C21: Multi-year (Permanent Height) | D21: 10 Items: 6 Tops, 4 Bottoms | E21: Essential Quality | F21: 0.2 | G21: Loungewear, Layering pieces | H21: Old Navy, Uniqlo basics, Joe Fresh | I21: 2 | J21: 20 | K21: =J21*I21 -> 40 | L21: =M21*67 -> 536 | M21: 8 | N21: =M21*I21 -> 16
B22: micro-text: Permanent sizing | E22: Premium Standard | F22: 0.6 | G22: Workwear, Outings | H22: Zara, Banana Republic, Levi's, Massimo Dutti | I22: 6 | J22: 50 | K22: =J22*I22 -> 300 | L22: =M22*67 -> 1340 | M22: 20 | N22: =M22*I22 -> 120
E23: High-End Exclusive | F23: 0.2 | G23: Investment pieces, Event wear | H23: Aritzia, Lululemon, Designer Labels | I23: 2 | J23: 120 | K23: =J23*I23 -> 240 | L23: =M23*67 -> 2680 | M23: 40 | N23: =M23*I23 -> 80
B24: Total | K24: =SUM(K21:K23) -> 580 | N24: =SUM(N21:N23) -> 216 | O24: ='Shipping Rate'!G5 -> 3 | P24: ='Shipping Rate'!H5 -> 6 | Q24: ='Shipping Rate'!I5 -> 4.5 | R24: 110 | S24: =R24+N24 -> 326 | T24: =K24-S24 -> 254
B26: Category | C26: Typical Buying Cycle | D26: Statement | E26: Savings Highlight | F26: General Thinking
B27: Babies & Toddlers (Ages 0-4) | C27: Every 3 to 6 months | D27: Your Typical Baby Wardrobe (Every 3-6 Months) | F27: Presenting the savings per cycle makes the abstract concept of cross-border shipping highly tangible.
B28: micro-text: Frequent size changes | D28: Most parents need about 24 items (14 tops & 10 bottoms) to keep up with growth and daily messes.
B30: Total | E30: You could save $116 every single growth cycle.
B31: Growing Kids (Ages 5-10) | C31: Every 12 months (Annual) | D31: Your Typical Kids Wardrobe (Annual Refresh) | F31: Because kids in this age group grow more predictably, their wardrobe shifts from "frequent small buys" to one larger "annual wardrobe refresh."
B32: micro-text: Steady, annual size updates | D32: For ages 5 to 10, most parents buy around 20 core items (12 tops & 8 bottoms) to build a wardrobe that lasts the entire school year.
B34: Total | E34: You could save $110 every single year, per child.
B35: Teens (Ages 11-17) | C35: Every 6 to 12 months (Variable) | D35: Your Typical Teen Wardrobe (Every 6-12 Months) | F35: In this phase, brand awareness becomes the primary driver. The overall item count is slightly lower, but the budget shifts heavily away from basic essentials and into popular name brands for daily wear.
B36: micro-text: Unpredictable growth spurts | D36: During growth spurts, most teens need about 17 core items (10 tops & 7 bottoms) per cycle, with a strong preference for popular brands.
B38: Total | E38: You could save $229 per cycle, per teen.
B39: Adults (Ages 18+) | C39: Multi-year (Permanent Height) | D39: Your Typical Adult Wardrobe (Annual Replenishment) | F39: Because adult sizing is permanent, the buying behavior shifts from replacing outgrown items to upgrading and replenishing an existing closet. The overall volume is lower, but the investment per piece is higher, with a strong emphasis on Premium Quality pieces for work or socializing.
B40: micro-text: Permanent sizing | D40: Adults generally maintain a permanent closet, buying around 10 core items (6 tops & 4 bottoms) per year to refresh basics and upgrade their style.
B42: Total | E42: You could save $254 on your annual wardrobe refresh.

Sheet Shipping Rate
A1: Mix | B1: Shipping Price | C1: Cad | F1: Category | G1: Summer | H1: Winter | I1: Mix
A2: 1 | B2: 3053 | C2: =B2/65 -> 46.969231 | F2: Babies & Toddlers (Ages 0-4) | G2: 2.1 | H2: 4.5 | I2: 3.5
A3: 1.5 | B3: 3577 | C3: =B3/65 -> 55.030769 | F3: Growing Kids | G3: 2.8 | H3: 5.8 | I3: 4.3
A4: 2 | B4: 4101 | C4: =B4/65 -> 63.092308 | F4: Teens | G4: 4 | H4: 7.3 | I4: 5.2
A5: 2.5 | B5: 4624 | C5: =B5/65 -> 71.138462 | F5: Adults | G5: 3 | H5: 6 | I5: 4.5
A6: 3 | B6: 5569 | C6: =B6/65 -> 85.676923
A7: 3.5 | B7: 6089 | C7: =B7/65 -> 93.676923
A8: 4 | B8: 6609 | C8: =B8/65 -> 101.67692
A9: 4.5 | B9: 7129 | C9: =B9/65 -> 109.67692
A10: 5 | B10: 7647 | C10: =B10/65 -> 117.64615
A11: 5.5 | B11: 8200 | C11: =B11/65 -> 126.15385
A12: 6 | B12: 9000 | C12: =B12/65 -> 138.46154
A13: 6.5 | B13: 9500 | C13: =B13/65 -> 146.15385
A14: 7 | B14: 10500 | C14: =B14/65 -> 161.53846
A15: 7.5 | B15: 11000 | C15: =B15/65 -> 169.23077
A16: 10 | B16: 12085 | C16: =B16/65 -> 185.92308
A18: Babies & Toddlers (Ages 0-4)
A19: The Garment Mix Matrix (24 Items: 14 Tops, 10 Bottoms)
A20: Essential (60% | 8 Tops, 6 Bottoms): Thin cottons, daily basics. (e.g., onesies, basic t-shirts, thin leggings, sweat-shorts).
A21: Premium Quality (35% | 5 Tops, 3 Bottoms): Structured or thicker fabrics. (e.g., woven shirts, hoodies, denim jeans, thick joggers, light jackets).
A22: High-End (5% | 1 Top, 1 Bottom): Heaviest structured pieces. (e.g., heavy outerwear/winter coat, premium knitwear, lined trousers).

Sheet For_why_use_Layo
A1: effective UI approaches to handle multiple selections:
A2: Approach 1: The "Household Total" with Accordions (Recommended)
A3: This method leads with the most powerful number—the combined savings—and allows the user to explore the details at their own pace.
A4: The Hook: Start with a combined total. For example: "💡 You could save $574 on your household wardrobe." (Combining the $210 Baby savings and $364 Adult savings).
A5: Approach 2: Tabbed Navigation
A6: If you want to keep the primary focus on the individual buying cycles rather than a massive combined number, tabs work perfectly.
A7: The Structure: Place a toggle or tab bar at the top of the comparison box.
A8: [ Babies & Toddlers ] | [ Adults ]
A9: The Interaction: The user taps a tab, and the content below switches to display the relevant 100% receipt for that category. This keeps the screen footprint small and focused.
A10: Approach 3: The Swipeable Carousel (Mobile-Optimized)
A11: If a large portion of your traffic will be on mobile devices, a card carousel is highly intuitive.
A12: The Structure: Each age group gets its own distinct "Comparison Card" containing the pie chart and the Canada vs. India receipt.
A13: The Interaction: The user simply swipes left or right to flip through their selected categories. You can include pagination dots at the bottom (• ◦ ◦) to indicate there are more profiles to view.

Sheet Category - Model for weight
A1: Category | B1: Attribute | C1: Subcategory | D1: Avg. Length (cm) | E1: Avg. Width (cm) | F1: Avg. Height (cm) | G1: Unit Volume (cm³) | H1: Actual Unit Weight (kg) | I1: Volumetric Divisor | J1: Volumetric Wt (kg) | K1: Billed Unit Wt (kg) | L1: Packaging Buffer (%)
A2: Clothing | B2: T-Shirts | C2: Light Topwear | D2: 25 | E2: 20 | F2: 2 | G2: 1000 | H2: 0.2 | I2: 5000 | J2: 0.2 | K2: 0.2 | L2: 0.05
A3: Clothing | B3: Casual Shirts | C3: Light Topwear | D3: 30 | E3: 20 | F3: 3 | G3: 1800 | H3: 0.25 | I3: 5000 | J3: 0.36 | K3: 0.36 | L3: 0.05
A4: Clothing | B4: Formal Shirts | C4: Light Topwear | D4: 30 | E4: 22 | F4: 3 | G4: 1980 | H4: 0.3 | I4: 5000 | J4: 0.396 | K4: 0.396 | L4: 0.05
A5: Clothing | B5: Blouses | C5: Light Topwear | D5: 25 | E5: 20 | F5: 2 | G5: 1000 | H5: 0.2 | I5: 5000 | J5: 0.2 | K5: 0.2 | L5: 0.05
A6: Clothing | B6: Tops | C6: Light Topwear | D6: 25 | E6: 20 | F6: 2 | G6: 1000 | H6: 0.15 | I6: 5000 | J6: 0.2 | K6: 0.2 | L6: 0.05
A7: Clothing | B7: Kurtis/Tunics | C7: Light Topwear | D7: 30 | E7: 25 | F7: 3 | G7: 2250 | H7: 0.35 | I7: 5000 | J7: 0.45 | K7: 0.45 | L7: 0.05
A8: Clothing | B8: Tank Tops | C8: Light Topwear | D8: 20 | E8: 15 | F8: 2 | G8: 600 | H8: 0.1 | I8: 5000 | J8: 0.12 | K8: 0.12 | L8: 0.05
A9: Clothing | B9: Jeans/Denim | C9: Heavy Bottoms | D9: 35 | E9: 25 | F9: 5 | G9: 4375 | H9: 0.6 | I9: 5000 | J9: 0.875 | K9: 0.875 | L9: 0.1
A10: Clothing | B10: Formal Trousers | C10: Heavy Bottoms | D10: 35 | E10: 25 | F10: 4 | G10: 3500 | H10: 0.5 | I10: 5000 | J10: 0.7 | K10: 0.7 | L10: 0.1
A11: Clothing | B11: Casual Pants/Chinos | C11: Heavy Bottoms | D11: 35 | E11: 25 | F11: 4 | G11: 3500 | H11: 0.45 | I11: 5000 | J11: 0.7 | K11: 0.7 | L11: 0.1
A12: Clothing | B12: Shorts | C12: Light Bottoms | D12: 25 | E12: 20 | F12: 3 | G12: 1500 | H12: 0.25 | I12: 5000 | J12: 0.3 | K12: 0.3 | L12: 0.05
A13: Clothing | B13: Skirts | C13: Light Bottoms | D13: 30 | E13: 25 | F13: 3 | G13: 2250 | H13: 0.3 | I13: 5000 | J13: 0.45 | K13: 0.45 | L13: 0.05
... A21: Clothing | B21: Blazers/Suit Jackets | C21: Heavy Ethnic & Party | D21: 45 | E21: 35 | F21: 10 | G21: 15750 | H21: 1 | I21: 5000 | J21: 3.15 | K21: 3.15 | L21: 0.15
A22: Clothing | B22: Raincoats | D22: 35 | E22: 25 | F22: 5 | G22: 4375 | H22: 0.4 | I22: 5000 | J22: 0.875 | K22: 0.875 | L22: 0.05
A23: Clothing | B23: Casual Dresses | C23: Light Dresses & Sets | D23: 30 | E23: 25 | F23: 4 | G23: 3000 | H23: 0.35 | I23: 5000 | J23: 0.6 | K23: 0.6 | L23: 0.05
A24: Clothing | B24: Formal Gowns | C24: Light Dresses & Sets | D24: 45 | E24: 35 | F24: 12 | G24: 18900 | H24: 1.2 | I24: 5000 | J24: 3.78 | K24: 3.78 | L24: 0.2
A25: Clothing | B25: Jumpsuits/Rompers | C25: Light Dresses & Sets | D25: 35 | E25: 25 | F25: 5 | G25: 4375 | H25: 0.4 | I25: 5000 | J25: 0.875 | K25: 0.875 | L25: 0.05
A26: Clothing | B26: Sarees (Lightweight) | C26: Light Dresses & Sets | D26: 35 | E26: 25 | F26: 5 | G26: 4375 | H26: 0.5 | I26: 5000 | J26: 0.875 | K26: 0.875 | L26: 0.05
A27: Clothing | B27: Sarees (Heavy/Bridal) | C27: Heavy Ethnic & Party | D27: 45 | E27: 35 | F27: 15 | G27: 23625 | H27: 2.5 | I27: 5000 | J27: 4.725 | K27: 4.725 | L27: 0.15
A28: Clothing | B28: Salwar Suits | C28: Heavy Ethnic & Party | D28: 35 | E28: 30 | F28: 8 | G28: 8400 | H28: 0.8 | I28: 5000 | J28: 1.68 | K28: 1.68 | L28: 0.1
A29: Clothing | B29: Lehengas (Heavy volume) | C29: Heavy Ethnic & Party | D29: 50 | E29: 40 | F29: 20 | G29: 40000 | H29: 3 | I29: 5000 | J29: 8 | K29: 8 | L29: 0.2
A30: Clothing | B30: Sherwanis | C30: Heavy Ethnic & Party | D30: 50 | E30: 40 | F30: 15 | G30: 30000 | H30: 2 | I30: 5000 | J30: 6 | K30: 6 | L30: 0.15
A31: Clothing | B31: Dhotis | D31: 30 | E31: 20 | F31: 4 | G31: 2400 | H31: 0.35 | I31: 5000 | J31: 0.48 | K31: 0.48 | L31: 0.05
A32: Clothing | B32: Undergarments/Lingerie | D32: 15 | E32: 10 | F32: 2 | G32: 300 | H32: 0.1 | I32: 5000 | J32: 0.06 | K32: 0.1 | L32: 0
A33: Clothing | B33: Thermals | D33: 25 | E33: 20 | F33: 4 | G33: 2000 | H33: 0.3 | I33: 5000 | J33: 0.4 | K33: 0.4 | L33: 0.05
A34: Clothing | B34: Sleepwear/Pajamas | D34: 30 | E34: 25 | F34: 4 | G34: 3000 | H34: 0.35 | I34: 5000 | J34: 0.6 | K34: 0.6 | L34: 0.05
A35: Clothing | B35: Bathrobes | D35: 40 | E35: 30 | F35: 10 | G35: 12000 | H35: 0.8 | I35: 5000 | J35: 2.4 | K35: 2.4 | L35: 0.1
A36: Clothing | B36: Gym T-Shirts | D36: 25 | E36: 20 | F36: 2 | G36: 1000 | H36: 0.2 | I36: 5000 | J36: 0.2 | K36: 0.2 | L36: 0.05
A37: Clothing | B37: Sports Bras | D37: 20 | E37: 15 | F37: 3 | G37: 900 | H37: 0.15 | I37: 5000 | J37: 0.18 | K37: 0.18 | L37: 0.05
A38: Clothing | B38: Yoga Pants | D38: 25 | E38: 20 | F38: 3 | G38: 1500 | H38: 0.25 | I38: 5000 | J38: 0.3 | K38: 0.3 | L38: 0.05
A39: Clothing | B39: Swimsuits | D39: 20 | E39: 15 | F39: 2 | G39: 600 | H39: 0.15 | I39: 5000 | J39: 0.12 | K39: 0.15 | L39: 0.05
A40: Clothing | B40: Tracksuits | D40: 35 | E40: 25 | F40: 8 | G40: 7000 | H40: 0.7 | I40: 5000 | J40: 1.4 | K40: 1.4 | L40: 0.1
A41: Clothing | B41: Socks | D41: 15 | E41: 10 | F41: 2 | G41: 300 | H41: 0.05 | I41: 5000 | J41: 0.06 | K41: 0.06 | L41: 0
A42: Clothing | B42: Scarves/Mufflers | D42: 20 | E42: 15 | F42: 3 | G42: 900 | H42: 0.15 | I42: 5000 | J42: 0.18 | K42: 0.18 | L42: 0.05
... A134: Home decor | B134: Incense Holders | D134: 25 | E134: 10 | F134: 5 | G134: 1250 | H134: 0.3 | I134: 5000 | J134: 0.25 | K134: 0.3 | L134: 0.1
